{
  "projectTypes": [
    { "name": "البنية التحتية", "value": 17, "percentage": 17 },
    { "name": "الطاقة", "value": 15, "percentage": 15 },
    { "name": "المياه", "value": 13, "percentage": 13 },
    { "name": "النقل", "value": 12, "percentage": 12 },
    { "name": "الإسكان", "value": 11, "percentage": 11 },
    { "name": "الصحة", "value": 10, "percentage": 10 },
    { "name": "التعليم", "value": 9, "percentage": 9 },
    { "name": "البيئة", "value": 7, "percentage": 7 },
    { "name": "الزراعة", "value": 6, "percentage": 6 }
  ],
  "projectPhases": [
    { "name": "التخطيط", "value": 15, "percentage": 15 },
    { "name": "التصميم", "value": 13, "percentage": 13 },
    { "name": "التنفيذ", "value": 12, "percentage": 12 },
    { "name": "المراجعة", "value": 11, "percentage": 11 },
    { "name": "الإغلاق", "value": 9, "percentage": 9 }
  ],
  "projectRegions": [
    { "name": "الرياض", "value": 20, "percentage": 20 },
    { "name": "مكة المكرمة", "value": 18, "percentage": 18 },
    { "name": "المدينة المنورة", "value": 15, "percentage": 15 },
    { "name": "المنطقة الشرقية", "value": 13, "percentage": 13 },
    { "name": "عسير", "value": 10, "percentage": 10 },
    { "name": "القصيم", "value": 8, "percentage": 8 },
    { "name": "حائل", "value": 7, "percentage": 7 }

  ],
  "programTimeline": {
    "years": ["2021", "2022", "2023", "2024", "2025", "2026"],
    "actual": [85, 92, 88, 95, 90, 0],
    "planned": [90, 95, 92, 98, 95, 97]
  },
  "geographicDistribution": [
    { 
      "region": "منطقة الرياض",
      "مبني": 25,
      "قيد الإنشاء": 15,
      "مخطط": 10,
      "متوقف": 5
    },
    { 
      "region": "مكة المكرمة",
      "مبني": 21,
      "قيد الإنشاء": 12,
      "مخطط": 8,
      "متوقف": 4
    },
    { 
      "region": "المدينة المنورة",
      "مبني": 19,
      "قيد الإنشاء": 10,
      "مخطط": 7,
      "متوقف": 3
    },
    { 
      "region": "المنطقة الشرقية",
      "مبني": 17,
      "قيد الإنشاء": 9,
      "مخطط": 6,
      "متوقف": 3
    },
    { 
      "region": "عسير",
      "مبني": 14,
      "قيد الإنشاء": 8,
      "مخطط": 5,
      "متوقف": 2
    },
    { 
      "region": "القصيم",
      "مبني": 11,
      "قيد الإنشاء": 6,
      "مخطط": 4,
      "متوقف": 2
    },
    { 
      "region": "حائل",
      "مبني": 9,
      "قيد الإنشاء": 5,
      "مخطط": 3,
      "متوقف": 1
    },
    { 
      "region": "تبوك",
      "مبني": 7,
      "قيد الإنشاء": 4,
      "مخطط": 2,
      "متوقف": 1
    },
    { 
      "region": "الجوف",
      "مبني": 6,
      "قيد الإنشاء": 3,
      "مخطط": 2,
      "متوقف": 1
    },
    { 
      "region": "الحدود الشمالية",
      "مبني": 5,
      "قيد الإنشاء": 3,
      "مخطط": 1,
      "متوقف": 1
    }
  ],
  "budgetMetrics": [
    { "category": "الميزانية المخصصة", "value": 1.38, "unit": "B" },
    { "category": "الميزانية المنفقة", "value": 1.05, "unit": "B" },
    { "category": "الميزانية المتبقية", "value": 0.33, "unit": "B" }
  ],
  "qualityClassifications": {
    "total": 6540,
    "data": [
      { "name": "ممتاز", "value": 1720, "percentage": 26 },
      { "name": "جيد جداً", "value": 1308, "percentage": 20 },
      { "name": "جيد", "value": 1243, "percentage": 19 },
      { "name": "مقبول", "value": 981, "percentage": 15 },
      { "name": "ضعيف", "value": 785, "percentage": 12 },
      { "name": "يحتاج تحسين", "value": 503, "percentage": 8 }
    ]
  },
  "complianceMetrics": {
    "total": 8825,
    "data": [
      { "name": "مطابق", "value": 3970, "percentage": 45 },
      { "name": "مطابق جزئياً", "value": 2647, "percentage": 30 },
      { "name": "غير مطابق", "value": 1324, "percentage": 15 },
      { "name": "قيد المراجعة", "value": 884, "percentage": 10 }
    ]
  },
  "staffTimeline": [
    { "month": "26-01", "المهندسون": 450, "الفنيون": 320, "الإداريون": 180 },
    { "month": "26-02", "المهندسون": 420, "الفنيون": 310, "الإداريون": 175 },
    { "month": "26-03", "المهندسون": 380, "الفنيون": 290, "الإداريون": 165 },
    { "month": "26-04", "المهندسون": 350, "الفنيون": 270, "الإداريون": 155 },
    { "month": "26-05", "المهندسون": 320, "الفنيون": 250, "الإداريون": 145 },
    { "month": "26-06", "المهندسون": 300, "الفنيون": 230, "الإداريون": 135 },
    { "month": "26-07", "المهندسون": 280, "الفنيون": 210, "الإداريون": 125 },
    { "month": "26-08", "المهندسون": 260, "الفنيون": 190, "الإداريون": 115 },
    { "month": "26-09", "المهندسون": 240, "الفنيون": 170, "الإداريون": 105 },
    { "month": "26-10", "المهندسون": 220, "الفنيون": 150, "الإداريون": 95 },
    { "month": "26-11", "المهندسون": 200, "الفنيون": 130, "الإداريون": 85 }
  ],
  "changeManagement": {
    "total": 14,
    "completed": 14,
    "percentage": 100
  },
  "nonCompliance": {
    "total": 35,
    "resolved": 29,
    "percentage": 83
  },
  "riskManagement": [
    { "id": 1, "project": "مشروع البنية التحتية الرقمية", "risk": "تأخير في التسليم", "level": "عالي", "status": "نشط" },
    { "id": 2, "project": "مشروع الطاقة المتجددة", "risk": "تجاوز الميزانية", "level": "متوسط", "status": "قيد المعالجة" },
    { "id": 3, "project": "مشروع شبكة المياه", "risk": "نقص الموارد البشرية", "level": "منخفض", "status": "مراقبة" },
    { "id": 4, "project": "مشروع النقل العام", "risk": "تغيير المتطلبات", "level": "عالي", "status": "نشط" },
    { "id": 5, "project": "مشروع الإسكان الاجتماعي", "risk": "مشاكل فنية", "level": "متوسط", "status": "قيد المعالجة" }
  ],
  "violatingProjects": [
    { "id": 1, "project": "مشروع التوسعة الشرقية", "deviation": "-4%", "impact": "عالي" },
    { "id": 2, "project": "مشروع الطرق السريعة", "deviation": "32%", "impact": "متوسط" },
    { "id": 3, "project": "مشروع المدارس الجديدة", "deviation": "-8%", "impact": "منخفض" },
    { "id": 4, "project": "مشروع المستشفيات", "deviation": "15%", "impact": "عالي" },
    { "id": 5, "project": "مشروع الحدائق العامة", "deviation": "-12%", "impact": "منخفض" }
  ],
  "projectStats": [
    { "metric": "إجمالي المشاريع", "value": "350", "trend": "+5%" },
    { "metric": "المشاريع النشطة", "value": "156", "trend": "+12%" },
    { "metric": "المشاريع المكتملة", "value": "194", "trend": "+8%" },
    { "metric": "نسبة الإنجاز الكلية", "value": "78%", "trend": "+3%" }
  ],
  "projectScatter": [
    { "x": 2, "y": 3, "size": 80, "label": "1", "color": "#10b981" },
    { "x": 3, "y": 4, "size": 100, "label": "2", "color": "#f59e0b" },
    { "x": 4, "y": 2, "size": 90, "label": "3", "color": "#ef4444" },
    { "x": 4.5, "y": 3.5, "size": 70, "label": "4", "color": "#8b5cf6" }
  ],
  "projectStatus": {
    "regular": 86,
    "late": 13,
    "onHold": 1
  }
}
